calculator/__init__.py
calculator/advanced/__init__.py
calculator/advanced/exponentiation.py
calculator/advanced/root.py
calculator/advanced/trigonometry/__init__.py
calculator/advanced/trigonometry/cosine.py
calculator/advanced/trigonometry/sine.py
calculator/advanced/trigonometry/tangent.py
calculator/basic/__init__.py
calculator/basic/addition.py
calculator/basic/multiplication.py
calculator/basic/subtraction.py
unidari-0.1.0.dist-info/LICENSE
unidari-0.1.0.dist-info/METADATA
unidari-0.1.0.dist-info/WHEEL
unidari-0.1.0.dist-info/top_level.txt
unidari-0.1.0.dist-info/RECORD
