Metadata-Version: 2.1
Name: unidari
Version: 0.1.0
Summary: Мега простой калькулятор на Python
Home-page: https://github.com/unidari
Author: daryana
Author-email: b.darya2809@gmail.com
Classifier: Programming Language :: Python :: 3
Classifier: License :: OSI Approved :: MIT License
Classifier: Operating System :: OS Independent
Requires-Python: >=3.6
License-File: LICENSE
